dummy_file_generator/__init__.py
dummy_file_generator/__main__.py
dummy_file_generator/data_files_handler.py
dummy_file_generator/configurables/__init__.py
dummy_file_generator/configurables/config.json
dummy_file_generator/configurables/settings.py
dummy_file_generator/data_files/__init__.py
dummy_file_generator/data_files/dates.txt
dummy_file_generator/data_files/first_names.txt
dummy_file_generator/data_files/ids.txt
dummy_file_generator/data_files/last_names.txt
dummy_file_generator/data_files/test.txt
dummy_file_generator/lib/__init__.py
dummy_file_generator/lib/csv_writer.py
dummy_file_generator/lib/flat_writer.py
dummy_file_generator/lib/utils.py
dummy_file_generator/tests/__init__.py
dummy_file_generator/tests/test_performance.py
dummy_file_generator/tests/test_unit.py
tests/__init__.py
tests/test_performance.py
tests/test_unit.py
dummy_file_generator-1.0.7.dist-info/LICENSE
dummy_file_generator-1.0.7.dist-info/METADATA
dummy_file_generator-1.0.7.dist-info/WHEEL
dummy_file_generator-1.0.7.dist-info/top_level.txt
dummy_file_generator-1.0.7.dist-info/RECORD
