Metadata-Version: 2.1
Name: dummy-file-generator
Version: 1.0.7
Summary: dummy flat text/csv file generator, typical usage scenario can be load / stress / performance testing of file-processing data tools
Home-page: https://github.com/datahappy1/dummy_file_generator
Author: datahappy1
Author-email: 
License: UNKNOWN
Platform: UNKNOWN
Classifier: Programming Language :: Python :: 3
Classifier: License :: OSI Approved :: MIT License
Classifier: Operating System :: OS Independent
